keyring/__init__.py
keyring/__main__.py
keyring/backend.py
keyring/backend_complete.bash
keyring/backend_complete.zsh
keyring/cli.py
keyring/completion.py
keyring/core.py
keyring/credentials.py
keyring/devpi_client.py
keyring/errors.py
keyring/http.py
keyring/py.typed
keyring/backends/SecretService.py
keyring/backends/Windows.py
keyring/backends/__init__.py
keyring/backends/chainer.py
keyring/backends/fail.py
keyring/backends/kwallet.py
keyring/backends/libsecret.py
keyring/backends/null.py
keyring/backends/macOS/__init__.py
keyring/backends/macOS/api.py
keyring/compat/__init__.py
keyring/compat/properties.py
keyring/compat/py312.py
keyring/compat/py38.py
keyring/testing/__init__.py
keyring/testing/backend.py
keyring/testing/util.py
keyring/util/__init__.py
keyring/util/platform_.py
keyring-25.5.0.dist-info/LICENSE
keyring-25.5.0.dist-info/METADATA
keyring-25.5.0.dist-info/WHEEL
keyring-25.5.0.dist-info/entry_points.txt
keyring-25.5.0.dist-info/top_level.txt
keyring-25.5.0.dist-info/RECORD
